<?xml version="1.0" encoding="utf-8" ?>
<dwsync>
<file name="alignvr-web.jpg" server="gpu.srv.ualberta.ca/public_html/" local="132306001789198560" remote="132306724000000000" Dst="2" />
<file name="arnet-web-01.jpg" server="gpu.srv.ualberta.ca/public_html/" local="132305413540166955" remote="132306724010000000" Dst="2" />
<file name="arnet-web-02.jpg" server="gpu.srv.ualberta.ca/public_html/" local="132306076177507663" remote="132306724010000000" Dst="2" />
<file name="arnet-web-03.jpg" server="gpu.srv.ualberta.ca/public_html/" local="132306076169360708" remote="132306724010000000" Dst="2" />
<file name="bear-beer-01.jpg" server="gpu.srv.ualberta.ca/public_html/" local="130275798351455239" remote="132306724020000000" Dst="2" />
<file name="bear-beer-02.jpg" server="gpu.srv.ualberta.ca/public_html/" local="130275798184355005" remote="132306724020000000" Dst="2" />
<file name="carna-annual-report_01.jpg" server="gpu.srv.ualberta.ca/public_html/" local="132306699738912347" remote="132306724030000000" Dst="2" />
<file name="carna-annual-report_02.jpg" server="gpu.srv.ualberta.ca/public_html/" local="132306703844650686" remote="132306724030000000" Dst="2" />
<file name="carna-annual-report_03.png" server="gpu.srv.ualberta.ca/public_html/" local="132306703369446635" remote="132306724030000000" Dst="2" />
<file name="carna-awards_01.jpg" server="gpu.srv.ualberta.ca/public_html/" local="132305343468066344" remote="132306724030000000" Dst="2" />
<file name="carna-awards_05.jpg" server="gpu.srv.ualberta.ca/public_html/" local="132306681715720522" remote="132306724040000000" Dst="2" />
<file name="carna-awards_02.jpg" server="gpu.srv.ualberta.ca/public_html/" local="132306684485098220" remote="132306724040000000" Dst="2" />
<file name="carna-awards_03.jpg" server="gpu.srv.ualberta.ca/public_html/" local="132306688472708142" remote="132306724040000000" Dst="2" />
<file name="carna-awards_04.jpg" server="gpu.srv.ualberta.ca/public_html/" local="132306688662449318" remote="132306724040000000" Dst="2" />
<file name="cars-with-stars-01.jpg" server="gpu.srv.ualberta.ca/public_html/" local="132306145645761219" remote="132306724040000000" Dst="2" />
<file name="cars-with-stars-02.jpg" server="gpu.srv.ualberta.ca/public_html/" local="132306144837285056" remote="132306724040000000" Dst="2" />
<file name="cars-with-stars-03.jpg" server="gpu.srv.ualberta.ca/public_html/" local="132306145469126994" remote="132306724050000000" Dst="2" />
<file name="cars-with-stars-04.jpg" server="gpu.srv.ualberta.ca/public_html/" local="132306145469316864" remote="132306724050000000" Dst="2" />
<file name="gamification-poster.jpg" server="gpu.srv.ualberta.ca/public_html/" local="132305898391927740" remote="132306724050000000" Dst="2" />
<file name="love-ya-party.jpg" server="gpu.srv.ualberta.ca/public_html/" local="132306102741971939" remote="132306724060000000" Dst="2" />
<file name="make-a-better-city_01.jpg" server="gpu.srv.ualberta.ca/public_html/" local="132306207122611843" remote="132306724060000000" Dst="2" />
<file name="make-a-better-city_02.jpg" server="gpu.srv.ualberta.ca/public_html/" local="132306207132012371" remote="132306724060000000" Dst="2" />
<file name="make-a-better-city_03.jpg" server="gpu.srv.ualberta.ca/public_html/" local="132306207116364834" remote="132306724070000000" Dst="2" />
<file name="make-a-better-city_04.jpg" server="gpu.srv.ualberta.ca/public_html/" local="132306217705518306" remote="132306724070000000" Dst="2" />
<file name="make-a-better-city_05.jpg" server="gpu.srv.ualberta.ca/public_html/" local="132306217793163478" remote="132306724070000000" Dst="2" />
<file name="qa-bakery.jpg" server="gpu.srv.ualberta.ca/public_html/" local="132305989643919799" remote="132306724070000000" Dst="2" />
<file name="tasko-parking-01.png" server="gpu.srv.ualberta.ca/public_html/" local="132306071950885296" remote="132306724080000000" Dst="2" />
<file name="tasko-parking-02.png" server="gpu.srv.ualberta.ca/public_html/" local="132306071943459919" remote="132306724080000000" Dst="2" />
<file name="tasko-parking-05.png" server="gpu.srv.ualberta.ca/public_html/" local="132306082589797518" remote="132306724080000000" Dst="2" />
<file name="tasko-parking-03.png" server="gpu.srv.ualberta.ca/public_html/" local="132306082598988114" remote="132306724080000000" Dst="2" />
<file name="tasko-parking-04.png" server="gpu.srv.ualberta.ca/public_html/" local="132306082609334062" remote="132306724080000000" Dst="2" />
<file name="vrcave-web-01.jpg" server="gpu.srv.ualberta.ca/public_html/" local="132398619707194874" remote="132398627070000000" Dst="2" />
<file name="vrcave-web-02.jpg" server="gpu.srv.ualberta.ca/public_html/" local="132398619712156190" remote="132398627070000000" Dst="2" />
<file name="world-junior-team1260_01.jpg" server="gpu.srv.ualberta.ca/public_html/" local="132306089889475644" remote="132306724090000000" Dst="2" />
<file name="world-junior-team1260_02.jpg" server="gpu.srv.ualberta.ca/public_html/" local="132306091815886825" remote="132306724100000000" Dst="2" />
<file name="vrcave-web-03.jpg" server="gpu.srv.ualberta.ca/public_html/" local="132398631428440682" remote="132398633080000000" Dst="2" />
</dwsync>